uw_saml2/VERSION
uw_saml2/__init__.py
uw_saml2/auth.py
uw_saml2/idp/__init__.py
uw_saml2/idp/attribute.py
uw_saml2/idp/federated.py
uw_saml2/idp/uw.py
uw_saml2/mock.py
uw_saml2/python3_saml.py
uw_saml2/sp.py
uw_saml-1.2.8.dist-info/LICENSE
uw_saml-1.2.8.dist-info/METADATA
uw_saml-1.2.8.dist-info/WHEEL
uw_saml-1.2.8.dist-info/RECORD
