Metadata-Version: 2.1
Name: uw-saml
Version: 1.2.8
Summary: A UW-specific adapter to the python3-saml package.
License: Apache 2.0
Requires-Python: >=3.7,<4.0
Classifier: License :: Other/Proprietary License
Classifier: Programming Language :: Python :: 3
Classifier: Programming Language :: Python :: 3.7
Classifier: Programming Language :: Python :: 3.8
Classifier: Programming Language :: Python :: 3.9
Classifier: Programming Language :: Python :: 3.10
Classifier: Programming Language :: Python :: 3.11
Classifier: Programming Language :: Python :: 3.12
Provides-Extra: python3-saml
Requires-Dist: Werkzeug (>=2.0.2,<3.0.0)
Requires-Dist: cachelib (>=0.4.1,<0.5.0)
Requires-Dist: onelogin (>=2.0.3,<3.0.0)
Requires-Dist: python3-saml (>=1.14.0,<2.0.0) ; extra == "python3-saml"
